emfreeze/__init__.py
emfreeze/__main__.py
emfreeze/cli.py
emfreeze/compile_build.py
emfreeze/copy_site_packages.py
emfreeze/download_embed.py
emfreeze-0.2.2.dist-info/LICENSE
emfreeze-0.2.2.dist-info/METADATA
emfreeze-0.2.2.dist-info/WHEEL
emfreeze-0.2.2.dist-info/entry_points.txt
emfreeze-0.2.2.dist-info/top_level.txt
emfreeze-0.2.2.dist-info/RECORD
