Metadata-Version: 2.1
Name: emfreeze
Version: 0.2.2
Summary: emfreeze is a commandline tool to freeze a venv in a standalone embeddeable packages
Home-page: https://github.com/swip3798/emfreeze
Author: Christian Schweigel
License: MIT License
Platform: UNKNOWN
Classifier: License :: OSI Approved :: MIT License
Classifier: Programming Language :: Python :: 3
Classifier: Programming Language :: Python :: 3.5
